code_pkg/__init__.py
code_pkg/cmd_line.py
code_pkg/app/__init__.py
code_pkg/app/ola.py
testtp/Req.py
testtp/__init__.py
testtp/__version__.py
testtp/cmd_line.py
testtp/logger.py
testtp/render.py
testtp/utils.py
testtp-0.0.3.dist-info/LICENSE
testtp-0.0.3.dist-info/METADATA
testtp-0.0.3.dist-info/WHEEL
testtp-0.0.3.dist-info/top_level.txt
testtp-0.0.3.dist-info/RECORD
