Metadata-Version: 2.1
Name: testtp
Version: 0.0.3
Summary: Http client for testers
Home-page: https://github.com/Be5yond/testtp
Author: Be5yond
Author-email: beyond147896@126.com
License: UNKNOWN
Platform: UNKNOWN
Classifier: Programming Language :: Python :: 3
Classifier: License :: OSI Approved :: Apache Software License
Classifier: Operating System :: OS Independent
Requires-Python: >=3.6
Requires-Dist: requests
Requires-Dist: pytest
Requires-Dist: schema
Requires-Dist: loguru
